metricks/__init__.py
metricks/charts.py
metricks/metadata.py
metricks/metric.py
metricks/pipelines.py
metricks/py.typed
metricks/session.py
metricks/sql.py
metricks-0.1.3.dist-info/METADATA
metricks-0.1.3.dist-info/WHEEL
metricks-0.1.3.dist-info/licenses/LICENSE
metricks-0.1.3.dist-info/RECORD
